cntp/__init__.py
cntp/module.py
cntp-0.0.10.dist-info/METADATA
cntp-0.0.10.dist-info/WHEEL
cntp-0.0.10.dist-info/licenses/LICENSE
cntp-0.0.10.dist-info/RECORD
