Metadata-Version: 2.1
Name: cntp
Version: 0.0.10
Summary: Converting numbers to Persian package
Project-URL: Homepage, https://github.com/pypa/sampleproject
Project-URL: Bug Tracker, https://github.com/pypa/sampleproject/issues
Author-email: Seyed Danial Alizadeh <mail.danial@yahoo.com>
License-File: LICENSE
Classifier: License :: OSI Approved :: MIT License
Classifier: Operating System :: OS Independent
Classifier: Programming Language :: Python :: 3
Requires-Python: >=3.7
